{
    "$schema": "https://docs.renovatebot.com/renovate-schema.json",
    "extends": [
        "config:base"
    ],
    "customManagers": [
        // Enable Ivy XML dependency updates
        {
            "customType": "regex",
            "managerFilePatterns": [
                "ivy.xml"
            ],
            "matchStrings": [
                "<dependency\\s+org=\"(?<groupId>[^\"]+?)\"\\s+name=\"(?<artifactId>[^\"]+?)\"\\s+rev=\"(?<currentValue>[^\"]+?)\"[^/>]*/>"
            ],
            "packageNameTemplate" : "{{groupId}}:{{artifactId}}",
            "datasourceTemplate": "maven",
        }
    ]
}
